seller_active/__info__.py
seller_active/__init__.py
seller_active/__version__.py
seller_active/api/__init__.py
seller_active/api/bundles/__init__.py
seller_active/api/bundles/bundles.py
seller_active/api/inventory/__init__.py
seller_active/api/inventory/inventory.py
seller_active/api/locations/__init__.py
seller_active/api/locations/locations.py
seller_active/api/orders/__init__.py
seller_active/api/orders/orders.py
seller_active/api/rate_limit_status/__init__.py
seller_active/api/rate_limit_status/rate_limit_status.py
seller_active/base/__init__.py
seller_active/base/api_response.py
seller_active/base/base.py
seller_active/base/helpers.py
python_seller_active-0.0.5.dist-info/LICENSE
python_seller_active-0.0.5.dist-info/METADATA
python_seller_active-0.0.5.dist-info/WHEEL
python_seller_active-0.0.5.dist-info/top_level.txt
python_seller_active-0.0.5.dist-info/RECORD
