Metadata-Version: 2.1
Name: python_seller_active
Version: 0.0.5
Summary: Wrapper around SellerActive.com API
Home-page: https://github.com/yberezkin/python_seller_active
Author: Yan Berezkin
Author-email: yan.berezkin@gmail.com
License: MIT
Project-URL: Bug Tracker, https://github.com/yberezkin/python_seller_active/issues
License-File: LICENSE
Requires-Dist: requests
